rsclimatelab/__init__.py
rsclimatelab/cli.py
rsclimatelab/dask_util.py
rsclimatelab/ecmwf.py
rsclimatelab/hydrogs.py
rsclimatelab/assets/rs_state.shp
rsclimatelab/assets/rs_state.shx
tests/__init__.py
rsclimatelab-0.3.0.dist-info/LICENSE
rsclimatelab-0.3.0.dist-info/METADATA
rsclimatelab-0.3.0.dist-info/WHEEL
rsclimatelab-0.3.0.dist-info/entry_points.txt
rsclimatelab-0.3.0.dist-info/top_level.txt
rsclimatelab-0.3.0.dist-info/RECORD
